oceanprotocol_job_details/__init__.py
oceanprotocol_job_details/di.py
oceanprotocol_job_details/domain.py
oceanprotocol_job_details/helpers.py
oceanprotocol_job_details/ocean.py
oceanprotocol_job_details/settings.py
oceanprotocol_job_details/loaders/__init__.py
oceanprotocol_job_details/loaders/loader.py
oceanprotocol_job_details/loaders/impl/__init__.py
oceanprotocol_job_details/loaders/impl/ddo.py
oceanprotocol_job_details/loaders/impl/files.py
oceanprotocol_job_details/loaders/impl/job_details.py
oceanprotocol_job_details-0.3.2.dist-info/METADATA
oceanprotocol_job_details-0.3.2.dist-info/WHEEL
oceanprotocol_job_details-0.3.2.dist-info/licenses/LICENSE
oceanprotocol_job_details-0.3.2.dist-info/RECORD
