Metadata-Version: 2.4
Name: oceanprotocol-job-details
Version: 0.3.2
Summary: A Python package to get details from OceanProtocol jobs
Project-URL: Homepage, https://github.com/AgrospAI/oceanprotocol-job-details
Project-URL: Issues, https://github.com/AgrospAI/oceanprotocol-job-details/issues
Author-email: Agrospai <agrospai@udl.cat>, Christian López García <christian.lopez@udl.cat>
License: Copyright 2025 Agrospai
License-File: LICENSE
Classifier: License :: OSI Approved :: MIT License
Classifier: Operating System :: OS Independent
Classifier: Programming Language :: Python :: 3
Requires-Python: >=3.10
Requires-Dist: aiofiles>=25.1.0
Requires-Dist: dependency-injector>=4.48.2
Requires-Dist: orjson>=3.11.3
Requires-Dist: pydantic-settings>=2.12.0
Requires-Dist: pydantic>=2.12.5
